COPYRIGHT
LICENSE
README.md
pyproject.toml
setup.py
simudo/__init__.py
simudo/matplotlib_backend.py
simudo/version.py
simudo.egg-info/PKG-INFO
simudo.egg-info/SOURCES.txt
simudo.egg-info/dependency_links.txt
simudo.egg-info/requires.txt
simudo.egg-info/top_level.txt
simudo/example/__init__.py
simudo/example/fourlayer/IV_Analysis.py
simudo/example/fourlayer/__init__.py
simudo/example/fourlayer/fourlayer.py
simudo/example/fourlayer/fourlayer_example.py
simudo/example/fourlayer/sweep_extraction.py
simudo/example/heterojunction/__init__.py
simudo/example/heterojunction/germanium.py
simudo/example/heterojunction/het1d_example.py
simudo/example/heterojunction/silicon.py
simudo/example/heterojunction/silicongermanium.py
simudo/example/marti2002/__init__.py
simudo/example/marti2002/colors.py
simudo/example/marti2002/marti2002.py
simudo/example/marti2002/marti2002_plot.py
simudo/example/pn_benchmark/__init__.py
simudo/example/pn_benchmark/pn_benchmark.py
simudo/example/pn_benchmark/pn_benchmark_create_submitfiles.py
simudo/example/pn_benchmark/pn_benchmark_plot.py
simudo/example/pn_diode/__init__.py
simudo/example/pn_diode/pn_diode.py
simudo/example/pn_diode/pn_diode_plot.py
simudo/fem/__init__.py
simudo/fem/adaptive_stepper.py
simudo/fem/assign.py
simudo/fem/debug_probe.py
simudo/fem/delayed_form.py
simudo/fem/dolfin_parameters.py
simudo/fem/expr.py
simudo/fem/extra_bindings.py
simudo/fem/ffc_jit_lock.py
simudo/fem/function_space.py
simudo/fem/function_space_cache.py
simudo/fem/function_subspace_registry.py
simudo/fem/ipython.py
simudo/fem/mesh_data.py
simudo/fem/mesh_util.py
simudo/fem/mesh_util1.py1
simudo/fem/newton_solver.py
simudo/fem/offset_partitioning.py
simudo/fem/plot.py
simudo/fem/spatial.py
simudo/fem/sympy_dolfin_printer.py
simudo/fem/ufl_extra.py
simudo/io/__init__.py
simudo/io/csv.py
simudo/io/h5yaml.py
simudo/io/output_writer.py
simudo/io/xdmf.py
simudo/memoize/__init__.py
simudo/memoize/memo.py
simudo/memoize/ufl.py
simudo/mesh/__init__.py
simudo/mesh/construction_helper.py
simudo/mesh/construction_helper_example.py
simudo/mesh/domaintag_mshr.py
simudo/mesh/facet.py
simudo/mesh/interval1dtag.py
