Metadata-Version: 1.1
Name: simudo
Version: 0.6.5.0
Summary: SIMUlation of Devices with Optics / SIMulateur Université D'Ottawa
Home-page: https://github.com/simudo/simudo
Author: Eduard Christian Dumitrescu
Author-email: eduard.c.dumitrescu@gmail.com
License: LGPLv3
Platform: UNKNOWN
Classifier: Intended Audience :: Science/Research
Classifier: License :: OSI Approved :: GNU Lesser General Public License v3 (LGPLv3)
Classifier: Programming Language :: Python :: 3 :: Only
Classifier: Topic :: Scientific/Engineering :: Electronic Design Automation (EDA)
Classifier: Topic :: Scientific/Engineering :: Physics
Classifier: Topic :: Software Development :: Libraries
